{
  "project_info": {
    "project_number": "912674683384",
    "project_id": "tripbuddy-dcd18",
    "storage_bucket": "tripbuddy-dcd18.appspot.com"
  },
  "client": [
    {
      "client_info": {
        "mobilesdk_app_id": "1:912674683384:android:9ef5249a856d827b62fe0d",
        "android_client_info": {
          "package_name": "com.tripbuddy"
        }
      },
      "oauth_client": [],
      "api_key": [
        {
          "current_key": "AIzaSyATHfYXMiCoU0x8XprXsTQilu9U_WQgMYQ"
        }
      ],
      "services": {
        "appinvite_service": {
          "other_platform_oauth_client": []
        }
      }
    }
  ],
  "configuration_version": "1"
}